VelocytoAnalysis/GRN.py
VelocytoAnalysis/__init__.py
VelocytoAnalysis/lineage.py
VelocytoAnalysis/model.py
VelocytoAnalysis/mst.py
VelocytoAnalysis/ode.py
VelocytoAnalysis-1.1.0.dist-info/LICENSE
VelocytoAnalysis-1.1.0.dist-info/METADATA
VelocytoAnalysis-1.1.0.dist-info/WHEEL
VelocytoAnalysis-1.1.0.dist-info/top_level.txt
VelocytoAnalysis-1.1.0.dist-info/RECORD
